honeydb/__init__.py
honeydb/api/__init__.py
honeydb/api/client.py
honeydb-1.5.0.data/scripts/honeydb
honeydb-1.5.0.dist-info/LICENSE
honeydb-1.5.0.dist-info/METADATA
honeydb-1.5.0.dist-info/WHEEL
honeydb-1.5.0.dist-info/top_level.txt
honeydb-1.5.0.dist-info/RECORD
