Metadata-Version: 2.1
Name: honeydb
Version: 1.5.0
Summary: A Python API wrapper and CLI tool for the HoneyDB.
Home-page: https://honeydb.io
Download-URL: https://github.com/honeydbio/honeydb-python
Author: foospidy
License: MIT
Keywords: wrapper library honeydb api cli
Classifier: Intended Audience :: Developers
Classifier: Topic :: Software Development :: Libraries :: Python Modules
Classifier: Programming Language :: Python :: 2.7
Classifier: License :: OSI Approved :: MIT License
License-File: LICENSE
Requires-Dist: requests
